api/README.md
api/__init__.py
api/bench_profile.py
api/data.py
api/entity.py
api/gld_feeder_generator.py
api/gridpiq.py
api/helpers.py
api/make_ems.py
api/metrics_api.py
api/metrics_base_api.py
api/metrics_collector.py
api/model_GLM.py
api/modify_GLM.py
api/parse_helpers.py
api/player.py
api/process_eplus.py
api/process_gld.py
api/process_houses.py
api/process_inv.py
api/process_pypower.py
api/process_voltages.py
api/recs_api.py
api/recs_gld_house_parameters.py
api/schedule_client.py
api/schedule_server.py
api/store.py
api/substation.py
api/test_runner.py
api/time_helpers.py
api/tso_PYPOWER.py
api/tso_helpers.py
api/tso_psst.py
api/datafiles/TESP_RECS.db
api/datafiles/feeder_defaults.json
api/datafiles/glm_classes.json
api/datafiles/grid_PIQ.json
consensus/__init__.py
consensus/case_merge.py
consensus/dg_agent.py
consensus/dso_agent.py
consensus/dso_market.py
consensus/forecasting.py
consensus/generator.py
consensus/glm_dictionary.py
consensus/microgrid.py
consensus/microgrid_agent.py
consensus/residential_feeder_glm.py
consensus/retail_market.py
consensus/substation.py
consensus/weather_agent.py
dsot/Wh_Energy_Purchases.py
dsot/__init__.py
dsot/balance_sheet_functions.py
dsot/battery_agent.py
dsot/case_comparison_plots.py
dsot/case_merge.py
dsot/customer_CFS.py
dsot/dso_CFS.py
dsot/dso_helper_functions.py
dsot/dso_map.py
dsot/dso_market.py
dsot/dso_quadratic_curves.py
dsot/dso_rate_making.py
dsot/ev_agent.py
dsot/forecasting.py
dsot/gen_map.py
dsot/generator_balance_sheet_func.py
dsot/glm_dictionary.py
dsot/helpers_dsot.py
dsot/hvac_agent.py
dsot/load_less_solar.py
dsot/map_results.py
dsot/plots.py
dsot/pv_agent.py
dsot/residential_feeder_glm.py
dsot/retail_market.py
dsot/sankey.py
dsot/solar.py
dsot/substation.py
dsot/substation_f.py
dsot/tou.py
dsot/water_heater_agent.py
dsot/wind_gen_year.py
matpower/__init__.py
matpower/matpower_dict.py
matpower/process_matpower.py
original/__init__.py
original/case_merge.py
original/commercial_feeder_glm.py
tesp_support-1.3.6.dist-info/AUTHORS
tesp_support-1.3.6.dist-info/LICENSE
tesp_support-1.3.6.dist-info/METADATA
tesp_support-1.3.6.dist-info/WHEEL
tesp_support-1.3.6.dist-info/entry_points.txt
tesp_support-1.3.6.dist-info/top_level.txt
tesp_support-1.3.6.dist-info/RECORD
