Metadata-Version: 2.1
Name: tesp_support
Version: 1.3.6
Summary: Python APIs for the Transactive Energy Simulation Platform
Author-email: Trevor Hardy <trevor.hardy@pnnl.gov>
Maintainer-email: Mitch Pelton <mitch.pelton@pnnl.gov>, Fred Rutz <fredrick.rutz@pnnl.gov>, Jessica Kerby <jessica.kerby@pnn.gov>, Nathan Gray <nathan.gray@pnnl.gov>, Trevor Hardy <trevor.hardy@pnnl.gov>
License: TESP License
Project-URL: Homepage, https://github.com/pnnl/tesp
Project-URL: Documentation, https://tesp.readthedocs.io
Project-URL: Repository, https://github.com/pnnl/tesp
Keywords: power system,transactive,energy
Classifier: Development Status :: 4 - Beta
Classifier: Environment :: Console
Classifier: Intended Audience :: Developers
Classifier: Intended Audience :: Education
Classifier: Intended Audience :: Science/Research
Classifier: License :: OSI Approved :: BSD License
Classifier: Natural Language :: English
Classifier: Operating System :: OS Independent
Classifier: Programming Language :: Python
Classifier: Programming Language :: Python :: 3.10
Classifier: Topic :: Scientific/Engineering
Requires-Python: >=3.10
License-File: LICENSE
License-File: AUTHORS
Requires-Dist: importlib-resources~=6.4.5
Requires-Dist: h5py~=3.12.1
Requires-Dist: helics~=3.5.3
Requires-Dist: pandas~=2.2.3
Requires-Dist: numpy~=1.26.4
Requires-Dist: scipy~=1.14.1
Requires-Dist: matplotlib~=3.9.2
Requires-Dist: networkx~=3.4.2
Requires-Dist: pyjson5~=1.6.7
Requires-Dist: PYPOWER==5.1.16
Requires-Dist: pyutilib==6.0.0
Requires-Dist: Pyomo==6.5.0
